bvx_pytest/__init__.py
bvx_pytest/defines.py
bvx_pytest/setup_function.py
bvx_pytest/teardown_function.py
bvx_pytest/es/__init__.py
bvx_pytest/es/defines.py
bvx_pytest/es/setup_function.py
bvx_pytest/es/teardown_function.py
bvx_pytest-0.0.22.dist-info/LICENSE
bvx_pytest-0.0.22.dist-info/METADATA
bvx_pytest-0.0.22.dist-info/WHEEL
bvx_pytest-0.0.22.dist-info/top_level.txt
bvx_pytest-0.0.22.dist-info/RECORD
